airflow_gitlab_webhook/__init__.py
airflow_gitlab_webhook/airflow_gitlab_webhook.py
airflow_gitlab_webhook/templates/__init__.py
airflow_gitlab_webhook/templates/index_admin.html
airflow_gitlab_webhook/templates/index_appbuilder.html
airflow_gitlab_webhook/templates/index_body.html
airflow_gitlab_webhook-1.0.1.dist-info/LICENSE
airflow_gitlab_webhook-1.0.1.dist-info/METADATA
airflow_gitlab_webhook-1.0.1.dist-info/WHEEL
airflow_gitlab_webhook-1.0.1.dist-info/entry_points.txt
airflow_gitlab_webhook-1.0.1.dist-info/top_level.txt
airflow_gitlab_webhook-1.0.1.dist-info/RECORD
